sniffgit/__init__.py
sniffgit/sniffgit.py
sniffgit-1.0.6.dist-info/DESCRIPTION.rst
sniffgit-1.0.6.dist-info/METADATA
sniffgit-1.0.6.dist-info/RECORD
sniffgit-1.0.6.dist-info/WHEEL
sniffgit-1.0.6.dist-info/entry_points.txt
sniffgit-1.0.6.dist-info/metadata.json
sniffgit-1.0.6.dist-info/top_level.txt
