Metadata-Version: 2.0
Name: sniffgit
Version: 1.0.6
Summary: Find sensitive information and files in a git repository.
Home-page: https://github.com/Liandy213/sniffgit
Author: Liandy Hardikoesoemo
Author-email: liandy.hardikoesoemo@gmail.com
License: ['MIT License']
Platform: UNKNOWN
Requires-Dist: colorama
